[
    {
        "id": "guarded_padded_vambrace",
        "name": "Guarded Padded Vambraces",
        "culture": "aserai",
        "weight": "0.6",
        "type": "HandArmor",
        "head_armor": "0",
        "body_armor": "0",
        "arm_armor": "9",
        "leg_armor": "0"
    },
    {
        "id": "ragged_armwraps",
        "name": "Ragged Armwraps",
        "culture": "battania",
        "weight": "0.4",
        "type": "HandArmor",
        "head_armor": "0",
        "body_armor": "0",
        "arm_armor": "3",
        "leg_armor": "0"
    },
    {
        "id": "armwraps",
        "name": "Armwraps",
        "culture": "battania",
        "weight": "0.2",
        "type": "HandArmor",
        "head_armor": "0",
        "body_armor": "0",
        "arm_armor": "3",
        "leg_armor": "0"
    },
    {
        "id": "guarded_armwraps",
        "name": "Guarded Armwraps",
        "culture": "battania",
        "weight": "0.4",
        "type": "HandArmor",
        "head_armor": "0",
        "body_armor": "0",
        "arm_armor": "7",
        "leg_armor": "0"
    },
    {
        "id": "rough_tied_bracers",
        "name": "Rough Tied Bracers",
        "culture": "battania",
        "weight": "0.6",
        "type": "HandArmor",
        "head_armor": "0",
        "body_armor": "0",
        "arm_armor": "9",
        "leg_armor": "0"
    },
    {
        "id": "buttoned_leather_bracers",
        "name": "Buttoned Leather Bracers",
        "culture": "battania",
        "weight": "0.5",
        "type": "HandArmor",
        "head_armor": "0",
        "body_armor": "0",
        "arm_armor": "4",
        "leg_armor": "0"
    },
    {
        "id": "strapped_leather_bracers",
        "name": "Strapped Leather Bracers",
        "culture": "battania",
        "weight": "0.5",
        "type": "HandArmor",
        "head_armor": "0",
        "body_armor": "0",
        "arm_armor": "5",
        "leg_armor": "0"
    },
    {
        "id": "roughtied_leather_bracers",
        "name": "Roughtied Leather Bracers",
        "culture": "battania",
        "weight": "0.5",
        "type": "HandArmor",
        "head_armor": "0",
        "body_armor": "0",
        "arm_armor": "3",
        "leg_armor": "0"
    },
    {
        "id": "battania_noble_bracers",
        "name": "Fian Bracers",
        "culture": "battania",
        "weight": "0.6",
        "type": "HandArmor",
        "head_armor": "0",
        "body_armor": "0",
        "arm_armor": "18",
        "leg_armor": "0"
    },
    {
        "id": "highland_gloves",
        "name": "Fur Rimmed Leather Gloves",
        "culture": "battania",
        "weight": "0.8",
        "type": "HandArmor",
        "head_armor": "0",
        "body_armor": "0",
        "arm_armor": "8",
        "leg_armor": "0"
    },
    {
        "id": "battania_warlord_bracers",
        "name": "Scale Warlord Bracers",
        "culture": "battania",
        "weight": "1.5",
        "type": "HandArmor",
        "head_armor": "0",
        "body_armor": "0",
        "arm_armor": "25",
        "leg_armor": "0"
    },
    {
        "id": "eastern_wrapped_armguards",
        "name": "Wrapped Armguards",
        "culture": "khuzait",
        "weight": "0.3",
        "type": "HandArmor",
        "head_armor": "0",
        "body_armor": "0",
        "arm_armor": "3",
        "leg_armor": "0"
    },
    {
        "id": "steppe_leather_vambraces",
        "name": "Leather Vambraces",
        "culture": "khuzait",
        "weight": "0.5",
        "type": "HandArmor",
        "head_armor": "0",
        "body_armor": "0",
        "arm_armor": "12",
        "leg_armor": "0"
    },
    {
        "id": "studded_leather_vambraces",
        "name": "Studded Leather Vambraces",
        "culture": "khuzait",
        "weight": "0.9",
        "type": "HandArmor",
        "head_armor": "0",
        "body_armor": "0",
        "arm_armor": "11",
        "leg_armor": "0"
    },
    {
        "id": "studded_vambraces",
        "name": "Studded Vambraces",
        "culture": "khuzait",
        "weight": "0.7",
        "type": "HandArmor",
        "head_armor": "0",
        "body_armor": "0",
        "arm_armor": "5",
        "leg_armor": "0"
    },
    {
        "id": "eastern_plated_leather_vambraces",
        "name": "Plated Leather Vambraces",
        "culture": "khuzait",
        "weight": "1.7",
        "type": "HandArmor",
        "head_armor": "0",
        "body_armor": "0",
        "arm_armor": "24",
        "leg_armor": "0"
    },
    {
        "id": "mail_mitten",
        "name": "Mail Mittens",
        "culture": "vlandia",
        "weight": "1.4",
        "type": "HandArmor",
        "head_armor": "0",
        "body_armor": "0",
        "arm_armor": "20",
        "leg_armor": "0"
    },
    {
        "id": "reinforced_mail_mitten",
        "name": "Reinforced Mail Mittens",
        "culture": "vlandia",
        "weight": "1.6",
        "type": "HandArmor",
        "head_armor": "0",
        "body_armor": "0",
        "arm_armor": "23",
        "leg_armor": "0"
    },
    {
        "id": "lordly_mail_mitten",
        "name": "Heavy Mail Mittens",
        "culture": "vlandia",
        "weight": "1.7",
        "type": "HandArmor",
        "head_armor": "0",
        "body_armor": "0",
        "arm_armor": "24",
        "leg_armor": "0"
    },
    {
        "id": "reinforced_leather_vambraces",
        "name": "Splint Vambraces",
        "culture": "vlandia",
        "weight": "1.0",
        "type": "HandArmor",
        "head_armor": "0",
        "body_armor": "0",
        "arm_armor": "20",
        "leg_armor": "0"
    },
    {
        "id": "northern_plated_gloves",
        "name": "Plate Reinforced Gloves",
        "culture": "sturgia",
        "weight": "1.5",
        "type": "HandArmor",
        "head_armor": "0",
        "body_armor": "0",
        "arm_armor": "18",
        "leg_armor": "0"
    },
    {
        "id": "northern_brass_bracers",
        "name": "Bronze Bracers",
        "culture": "sturgia",
        "weight": "1.3",
        "type": "HandArmor",
        "head_armor": "0",
        "body_armor": "0",
        "arm_armor": "22",
        "leg_armor": "0"
    },
    {
        "id": "woven_leather_bracers",
        "name": "Woven Leather Bracers",
        "culture": "empire",
        "weight": "0.8",
        "type": "HandArmor",
        "head_armor": "0",
        "body_armor": "0",
        "arm_armor": "6",
        "leg_armor": "0"
    },
    {
        "id": "padded_mitten",
        "name": "Padded Mittens",
        "culture": "empire",
        "weight": "0.6",
        "type": "HandArmor",
        "head_armor": "0",
        "body_armor": "0",
        "arm_armor": "9",
        "leg_armor": "0"
    },
    {
        "id": "plated_strip_gauntlets",
        "name": "Plated Striped Vambraces",
        "culture": "empire",
        "weight": "1.4",
        "type": "HandArmor",
        "head_armor": "0",
        "body_armor": "0",
        "arm_armor": "22",
        "leg_armor": "0"
    },
    {
        "id": "lamellar_plate_gauntlets",
        "name": "Lamellar Plate Gauntlets",
        "culture": "empire",
        "weight": "1.8",
        "type": "HandArmor",
        "head_armor": "0",
        "body_armor": "0",
        "arm_armor": "23",
        "leg_armor": "0"
    },
    {
        "id": "decorated_imperial_gauntlets",
        "name": "Decorated Imperial Gauntlets",
        "culture": "empire",
        "weight": "1.5",
        "type": "HandArmor",
        "head_armor": "0",
        "body_armor": "0",
        "arm_armor": "20",
        "leg_armor": "0"
    },
    {
        "id": "lordly_padded_mitten",
        "name": "Lordly Padded Mittens",
        "culture": "empire",
        "weight": "1.3",
        "type": "HandArmor",
        "head_armor": "0",
        "body_armor": "0",
        "arm_armor": "18",
        "leg_armor": "0"
    },
    {
        "id": "reinforced_padded_mitten",
        "name": "Reinforced Padded Mittens",
        "culture": "empire",
        "weight": "0.9",
        "type": "HandArmor",
        "head_armor": "0",
        "body_armor": "0",
        "arm_armor": "18",
        "leg_armor": "0"
    },
    {
        "id": "leather_gloves",
        "name": "Leather Gloves",
        "culture": "neutral_culture",
        "weight": "0.4",
        "type": "HandArmor",
        "head_armor": "0",
        "body_armor": "0",
        "arm_armor": "4",
        "leg_armor": "0"
    },
    {
        "id": "padded_vambrace",
        "name": "Padded Vambraces",
        "culture": "neutral_culture",
        "weight": "0.1",
        "type": "HandArmor",
        "head_armor": "0",
        "body_armor": "0",
        "arm_armor": "7",
        "leg_armor": "0"
    }
]